[
    {
        "title": "Where do foreigners live in Kuala Lumpur",
        "description": "A modern high-rise project with breathtaking views.",The place foreigner and expatriate will choose to stay upon arrival in Kuala Lumpur usually depending on a few reasons. The area they choose heavily depend on whether they come for work, for children's education, for business or retirement. The main areas with heavy foreign community: #KLCC #Mon't Kiara #DesaParkCity. Grab this opportunity to understand more about this location, environment, the township offers and the price of these three locations. Our recent Malaysia Premium Visa Programme (PVIP) and revamping the Malaysia My Second Home Programme (MM2H) scheme has led many foreigners to move to Malaysia
        "price": "RM",
        "image": "images/Where do foreigners live in Kuala Lumpur.jpg",
        "video": "https://www.youtube.com/embed/LyvJjY2xnDU"  // YouTube video link
    },
    {
        "title": "Beachfront Residences",
        "description": "Luxurious living by the beach, with premium amenities.",
        "price": "$1,000,000",
        "image": "images/beachfront-residences.jpg",
        "video": "https://www.youtube.com/embed/your_video_id"  // YouTube video link
    },
    {
        "title": "City Centre Loft",
        "description": "Contemporary living in the heart of the city.",
        "price": "$650,000",
        "image": "images/city-centre-loft.jpg",
        "video": "https://www.youtube.com/embed/your_video_id"  // YouTube video link
    }
]
